CHANGELOG.md
majormode/__init__.py
majormode/photoidmagick.py
photoidmagick-1.1.11.dist-info/LICENSE
photoidmagick-1.1.11.dist-info/WHEEL
photoidmagick-1.1.11.dist-info/entry_points.txt
photoidmagick-1.1.11.dist-info/METADATA
photoidmagick-1.1.11.dist-info/RECORD
