Metadata-Version: 2.1
Name: photoidmagick
Version: 1.1.11
Summary: Python library to automatically align and crop your photos to the correct biometric passport photo size
Home-page: https://github.com/majormode/photoidmagick-python-library
License: SEE LICENSE IN <LICENSE.md>
Keywords: photo,library,biometric,passport,cli
Author: Daniel CAUNE
Author-email: daniel.caune@gmail.com
Requires-Python: >=3.9,<4.0
Classifier: Development Status :: 5 - Production/Stable
Classifier: License :: OSI Approved :: MIT License
Classifier: License :: Other/Proprietary License
Classifier: Operating System :: OS Independent
Classifier: Programming Language :: Python
Classifier: Programming Language :: Python :: 3
Classifier: Programming Language :: Python :: 3.9
Classifier: Programming Language :: Python :: 3.10
Classifier: Programming Language :: Python :: 3.11
Classifier: Topic :: Software Development :: Libraries
Requires-Dist: dlib
Requires-Dist: exifread
Requires-Dist: face-recognition
Requires-Dist: numpy
Requires-Dist: perseus-core-library
Requires-Dist: pillow
Project-URL: Repository, https://github.com/majormode/photoidmagick-python-library
